mattdaemon/__init__.py
mattdaemon/daemon.py
mattdaemon/example.py
mattdaemon_py3-1.1.2.dist-info/METADATA
mattdaemon_py3-1.1.2.dist-info/WHEEL
mattdaemon_py3-1.1.2.dist-info/top_level.txt
mattdaemon_py3-1.1.2.dist-info/RECORD
