Metadata-Version: 2.1
Name: mattdaemon-py3
Version: 1.1.2
Summary: Easily daemonize your python projects
Home-page: https://github.com/catchmaurya/mattdaemon_py3
Author: Maurya Allimuthu
Author-email: catchmaurya@gmail.com
License: UNKNOWN
Keywords: daemon daemonize daemonise cli matt
Platform: UNKNOWN
Classifier: Programming Language :: Python :: 3
Classifier: License :: OSI Approved :: MIT License
Classifier: Operating System :: OS Independent
